hello_meghana/__init__.py
hello_meghana/cli.py
hello_meghanab-0.36.dist-info/METADATA
hello_meghanab-0.36.dist-info/WHEEL
hello_meghanab-0.36.dist-info/entry_points.txt
hello_meghanab-0.36.dist-info/top_level.txt
hello_meghanab-0.36.dist-info/RECORD
