Metadata-Version: 2.1
Name: hello-meghanab
Version: 0.36
Summary: A hello  gitlab World package
Home-page: UNKNOWN
Author: megha
Author-email: meghanabl2112@gmail.com
License: UNKNOWN
Platform: UNKNOWN
Requires-Dist: click
